[
  {
    "id": 1,
    "serviceTitle": "Teeth Whitening",
    "imageUrl": "https://encrypted-tbn0.gstatic.com/images?q=tbn:ANd9GcTZp3drU4_AkWNb4PlptQpQPuU1myIobyGWdg&s",
    "description": "Professional teeth whitening to restore your bright, white smile.",
    "cost": 150
  },
  {
    "id": 2,
    "serviceTitle": "Dental Implants",
    "imageUrl": "https://www.perio.org/wp-content/uploads/2020/02/dental-implant.png",
    "description": "Permanent solution for missing teeth with durable dental implants.",
    "cost": 2000
  },
  {
    "id": 3,
    "serviceTitle": "Orthodontic Braces",
    "imageUrl": "https://encrypted-tbn0.gstatic.com/images?q=tbn:ANd9GcS2t0m1TNBWYiRFbPmucFM3X0sYuyoYnrnoIg&s",
    "description": "Advanced braces for straightening teeth and correcting alignment.",
    "cost": 2500
  },
  {
    "id": 4,
    "serviceTitle": "Root Canal Treatment",
    "imageUrl": "https://images.squarespace-cdn.com/content/v1/53539894e4b0e85fd9202881/1678154327960-RAF164AZB8SBREELWPJW/cc-dental-root-canal-diagram.jpg",
    "description": "Effective root canal therapy to save and repair damaged teeth.",
    "cost": 800
  },
  {
    "id": 5,
    "serviceTitle": "Dental Cleaning",
    "imageUrl": "https://hammonddent.com/wp-content/uploads/2023/08/dental-cleaning-removing.jpg",
    "description": "Routine dental cleaning to maintain oral hygiene and health.",
    "cost": 100
  }
]
